tempered/__init__.py
tempered/py.typed
tempered/_internals/__init__.py
tempered/_internals/escape.py
tempered/src/errors.py
tempered/src/module.py
tempered/src/tempered.py
tempered/src/types.py
tempered/src/compiling/__init__.py
tempered/src/compiling/accumulators.py
tempered/src/compiling/builder.py
tempered/src/compiling/calls.py
tempered/src/compiling/constants.py
tempered/src/compiling/css.py
tempered/src/compiling/dependencies.py
tempered/src/compiling/module.py
tempered/src/compiling/resolve.py
tempered/src/compiling/rules.py
tempered/src/compiling/template.py
tempered/src/compiling/validate.py
tempered/src/css/extract.py
tempered/src/css/postprocess.py
tempered/src/css/sass.py
tempered/src/css/scoped.py
tempered/src/parsing/__init__.py
tempered/src/parsing/metadata.py
tempered/src/parsing/nodes.py
tempered/src/parsing/parser.py
tempered/src/template/introspection.py
tempered/src/template/postprocess.py
tempered/src/template/template.py
tempered/src/utils/ast_utils.py
tempered/src/utils/find.py
tempered/src/utils/minify.py
tempered/src/utils/soup.py
tempered-0.11.0.dist-info/LICENSE
tempered-0.11.0.dist-info/WHEEL
tempered-0.11.0.dist-info/METADATA
tempered-0.11.0.dist-info/RECORD
