Metadata-Version: 2.3
Name: tempered
Version: 0.11.0
Summary: A fast, strongly typed html templating library for python
Author-email: Ben Brady <benbrady04.bb@gmail.com>
Requires-Python: >=3.9
Classifier: License :: OSI Approved :: MIT License
Requires-Dist: beautifulsoup4~=4.12.2
Requires-Dist: minify-html~=0.15.0
Requires-Dist: tinycss2~=1.2.1
Requires-Dist: rcssmin!=1.1.2
Requires-Dist: strictyaml==1.7.3
Requires-Dist: typing_extensions
Requires-Dist: libsass ; extra == "all"
Requires-Dist: lxml ; extra == "all"
Requires-Dist: black ; extra == "dev"
Requires-Dist: isort ; extra == "dev"
Requires-Dist: autoflake ; extra == "dev"
Requires-Dist: Flake8-pyproject ; extra == "dev"
Requires-Dist: black ; extra == "docs"
Requires-Dist: mkdocs ; extra == "docs"
Requires-Dist: mkdocs-material ; extra == "docs"
Requires-Dist: mkdocstrings[crystal, python] ; extra == "docs"
Requires-Dist: libsass ; extra == "sass"
Requires-Dist: pytest ; extra == "test"
Requires-Dist: pytest-asyncio ; extra == "test"
Requires-Dist: mypy ; extra == "test"
Provides-Extra: all
Provides-Extra: dev
Provides-Extra: docs
Provides-Extra: sass
Provides-Extra: test
